{"resource_state":3,"athlete":{"id":42223740,"resource_state":1},"name":"Sortie à vélo le soir","distance":21162.7,"moving_time":4130,"elapsed_time":5901,"total_elevation_gain":23.8,"type":"Ride","sport_type":"Ride","workout_type":null,"id":3757329634,"start_date":"2020-07-13T16:15:00Z","start_date_local":"2020-07-13T18:15:00Z","timezone":"(GMT+01:00) Europe/Paris","utc_offset":7200,"location_city":null,"location_state":null,"location_country":"France","achievement_count":2,"kudos_count":0,"comment_count":0,"athlete_count":1,"photo_count":0,"map":{"id":"a3757329634","polyline":"kklpGxboFNUL_@^g@\\Ur@WZWHEXD^b@Zt@LPRHT?f@N|@n@Z@b@Sv@q@b@OpDBj@BPNX^RJz@DJCFIPy@DeEHyANa@RMj@WpAJ^Vl@Zx@t@l@b@bCfCTFVETGnB_Ad@M`@EpANHAFCHUx@{BDIFEdACrABNGFYb@eDDk@XyAPaB@a@?gCQiBi@gI@qBHqBFi@Hc@Ra@^k@VSlAkA`@m@v@cCh@kBVoAl@sBTe@h@kBn@sAHYf@g@d@]p@MP?^DnABlCXl@Bp@ATGrAa@f@c@nC}AXYtAq@p@c@ZE\\MhB[n@QfB]f@_@Xe@P}@PoANc@Lg@L{@H_AVkBx@_F\\yCBg@CmAIqA_AwDy@{DkAyEe@cBq@aBy@gAw@g@g@Q[Ey@?_ANw@R_Bf@sALcACgASKGg@M}Au@s@g@y@q@qAkAq@aAi@_Ai@}A]{Ai@oDM{AA{ANkEC{@OiB_@mBmAgDq@qAu@gAcAuBMS_@yA[kB_@yAu@yAu@eAoAsAm@cAY{@UmAUsA]}AaAeCWkAQcAKgB]{DCw@DoD@g@HY^S~@u@xC}C`AoBjAqCh@y@~@iAt@o@rAqAfEsDvBwB~@s@fAqAl@i@dAgAhAuAVo@r@iDb@_Bt@gCd@cA|@eAv@_@t@W|@Uh@[^i@l@uALg@bAeFd@uCNa@`@uBj@eCh@wCr@wCXyAf@yCDcCLs@Xo@FCLHdFfFNDb@@FBDDBNGJA]]OKFSQ_CaCs@y@w@s@I?MFYr@EBMAuCgBu@WQCm@{@c@cAc@gAeBaCsCgFc@aAyA{D]qBYeAy@yB[eBi@yCM{AGuAW_Be@gKWiIc@{KCYEUm@gBMi@Gg@n@wEHgAAiCJwOt@{MFwB^eDAa@Du@R}ALk@dCqF`C_K~@gDd@uBb@}Ap@uCDCzMdBx@PP@~BVrAD|AAjAEdBQv@OtBe@jBk@x@[jEgChAy@pAmAdAgAVSdEoG^ERUC]Hk@nBwEvBwD|@qAbAgAbAsAjAoBzMgU\\i@\\s@|EmIjD{FvKiR|DqGnGyK`C}DdA}AtC{DjC}C|a@cc@h@{@`LiLtCuDnB_DFEJBPx@Uq@@i@t@kAN[Tm@R_@nBgDt@eBbAqB`AuAl@oANOf@[x@aANK~@eA~AsCx@oAPi@zAwCnBqE|AyDVc@Ry@`CyFhAyC|AkDfFqMzC_HLe@bDcIh@{Af@iAvAoDp@{AdCcGtBsFxAkDhCsGVg@Z_Ah@oAfJoUrAsCnA}BhCwDv@cA~@eATSdBaBbBqAdAu@|DaCbC}AbEgCD@FJFlABTB@DAbAg@LBDD`IjU`@fAHNTPx@dAJAn@e@pImHPc@ZkALYDAXNZ@f@KJSn@kFfAaF","resource_state":3,"summary_polyline":"kklpGxboF\\u@^g@\\Ur@Wd@]XD^b@Zt@LPpAX|@n@Z@b@Sv@q@b@O|EFPNX^RJfA@FIPy@DeEHyANa@~@e@pAJlAr@x@t@l@b@bCfCTFl@MnB_Ad@M`@EzALFCHUx@{BLOdACrABNGj@_EDk@XyARcC?gCQiBi@gI@qBHqBFi@Hc@r@mAdB_B`@m@v@cCh@kBVoAl@sBTe@h@kBn@sAHYlAeAp@M`CHzD\\fAIrAa@f@c@nC}AXYtAq@p@c@zH_Bf@_@Xe@P}@PoA\\kAn@gFx@_F\\yCBg@CmAIqA_AwDy@{DkAyEe@cBq@aBy@gAw@g@g@Q[Ey@?wBb@_Bf@sALcACgASs@U}Au@mByAqAkAq@aAi@_Ai@}A]{Ai@oDM{AA{ANkEC{@OiB_@mBmAgDq@qAu@gAqAiC_@yA[kB_@yAu@yAu@eAoAsAm@cAY{@k@aD]}AaAeCWkAQcAKgBa@sFDoD@g@HY^S~@u@xC}C`AoBjAqCh@y@~@iApIuHvBwB~@s@fAqAl@i@dAgAhAuAVo@r@iDb@_Bt@gCd@cA|@eAv@_@rBm@h@[^i@l@uALg@bAeFd@uCNa@`@uBj@eCh@wClAqFf@yCDcCLs@Xo@FCLHdFfFNDj@DDDBNGJA]]OKFSQsD{Dw@s@I?MFYr@S@uCgBgA[m@{@gAkCeBaCsCgF}B}F]qBYeAy@yB[eBi@yCM{AGuAW_Be@gKWiIc@{KIo@m@gBUqAn@wEHgAAiCJwOt@{MFwB^eDBwAR}ALk@dCqF`C_K~@gDzBiJDCzMdBx@PpCXrADhDG|Ca@tBe@dDgAjEgChAy@vCuCVSdEoG^ERUC]Hk@nBwEvBwD|@qAbAgAbAsAjAoBzMgU\\i@zFaKjD{FvKiR|DqGpKwQdA}AtC{DjC}C|a@cc@h@{@`LiLtCuDnB_DFEJBPx@Uq@@i@t@kAx@iBnBgDt@eBbAqB`AuAl@oAv@k@x@aANK~@eA~AsCx@oAPi@zAwClEkKVc@Ry@jEsK|AkDfFqMzC_HLe@bDcIh@{Af@iAvAoDvD_JtBsFxAkDhCsGVg@Z_ApK_XrAsCnA}BhCwDv@cA~@eAzBuBbBqAdAu@dOgJLLFlABTH?bAg@LBDDbJrWHNTPx@dAJA`KsIPc@h@eBDAt@Pf@KJSn@kFfAaF"},"trainer":false,"commute":false,"manual":false,"private":false,"visibility":"everyone","flagged":false,"gear_id":null,"start_latlng":[44.796868,-1.229401],"end_latlng":[44.717378,-1.067399],"average_speed":5.124,"max_speed":7.7,"has_heartrate":true,"average_heartrate":113.6,"max_heartrate":137,"heartrate_opt_out":false,"display_hide_heartrate_option":true,"elev_high":11.9,"elev_low":4.6,"upload_id":4014277136,"upload_id_str":"4014277136","external_id":"garmin_push_5232044883","from_accepted_tag":false,"pr_count":2,"total_photo_count":0,"has_kudoed":false,"description":null,"calories":462,"perceived_exertion":null,"prefer_perceived_exertion":null,"segment_efforts":[{"id":2717827540345799700,"resource_state":2,"name":"Vers Lège par la foret","activity":{"id":3757329634,"resource_state":1},"athlete":{"id":42223740,"resource_state":1},"elapsed_time":1153,"moving_time":1153,"start_date":"2020-07-13T16:20:04Z","start_date_local":"2020-07-13T18:20:04Z","distance":6203.9,"start_index":111,"end_index":432,"device_watts":false,"average_heartrate":121.5,"max_heartrate":137,"segment":{"id":20882094,"resource_state":2,"name":"Vers Lège par la foret","activity_type":"Ride","distance":6203.9,"average_grade":0,"maximum_grade":6,"elevation_high":-5,"elevation_low":-11.6,"start_latlng":[44.786156,-1.224905],"end_latlng":[44.77773,-1.170673],"elevation_profile":null,"climb_category":0,"city":"Lège-Cap-Ferret","state":"Nouvelle-Aquitaine","country":"France","private":false,"hazardous":false,"starred":false},"pr_rank":null,"achievements":[],"hidden":false},{"id":2717827540345428000,"resource_state":2,"name":"Arès vers Andernos","activity":{"id":3757329634,"resource_state":1},"athlete":{"id":42223740,"resource_state":1},"elapsed_time":266,"moving_time":266,"start_date":"2020-07-13T17:04:59Z","start_date_local":"2020-07-13T19:04:59Z","distance":1544.9,"start_index":700,"end_index":748,"device_watts":false,"average_heartrate":111.3,"max_heartrate":116,"segment":{"id":11175462,"resource_state":2,"name":"Arès vers Andernos","activity_type":"Ride","distance":1544.9,"average_grade":-0.7,"maximum_grade":2.4,"elevation_high":16.7,"elevation_low":5.4,"start_latlng":[44.760147,-1.119625],"end_latlng":[44.749641,-1.106907],"elevation_profile":null,"climb_category":0,"city":"Ares","state":"Aquitaine","country":"France","private":false,"hazardous":false,"starred":false},"pr_rank":1,"achievements":[{"type_id":3,"type":"pr","rank":1}],"hidden":false},{"id":2717827540348469000,"resource_state":2,"name":"entre Andernos et Taussat ","activity":{"id":3757329634,"resource_state":1},"athlete":{"id":42223740,"resource_state":1},"elapsed_time":159,"moving_time":159,"start_date":"2020-07-13T17:45:53Z","start_date_local":"2020-07-13T19:45:53Z","distance":813.4,"start_index":911,"end_index":944,"device_watts":false,"average_heartrate":107.9,"max_heartrate":116,"segment":{"id":18681656,"resource_state":2,"name":"entre Andernos et Taussat ","activity_type":"Ride","distance":813.4,"average_grade":0,"maximum_grade":0.2,"elevation_high":9.1,"elevation_low":8.7,"start_latlng":[44.730858,-1.075393],"end_latlng":[44.72552,-1.068616],"elevation_profile":null,"climb_category":0,"city":"Andernos-les-Bains","state":"Nouvelle-Aquitaine","country":"France","private":false,"hazardous":false,"starred":false},"pr_rank":null,"achievements":[],"hidden":false}],"splits_metric":[{"distance":1010.4,"elapsed_time":194,"elevation_difference":-0.8,"moving_time":194,"split":1,"average_speed":5.21,"average_grade_adjusted_speed":null,"average_heartrate":112.23195876288659,"pace_zone":0},{"distance":1004.7,"elapsed_time":194,"elevation_difference":1.9,"moving_time":194,"split":2,"average_speed":5.18,"average_grade_adjusted_speed":null,"average_heartrate":120,"pace_zone":0},{"distance":985.7,"elapsed_time":180,"elevation_difference":-2.3,"moving_time":180,"split":3,"average_speed":5.48,"average_grade_adjusted_speed":null,"average_heartrate":118.84444444444445,"pace_zone":0},{"distance":1019.9,"elapsed_time":196,"elevation_difference":1.6,"moving_time":196,"split":4,"average_speed":5.2,"average_grade_adjusted_speed":null,"average_heartrate":119.29591836734694,"pace_zone":0},{"distance":982.4,"elapsed_time":190,"elevation_difference":0.4,"moving_time":190,"split":5,"average_speed":5.17,"average_grade_adjusted_speed":null,"average_heartrate":121.2421052631579,"pace_zone":0},{"distance":1006.1,"elapsed_time":186,"elevation_difference":0.2,"moving_time":186,"split":6,"average_speed":5.41,"average_grade_adjusted_speed":null,"average_heartrate":120.23655913978494,"pace_zone":0},{"distance":1010.3,"elapsed_time":173,"elevation_difference":-4.8,"moving_time":173,"split":7,"average_speed":5.84,"average_grade_adjusted_speed":null,"average_heartrate":121.95375722543352,"pace_zone":0},{"distance":1007.5,"elapsed_time":169,"elevation_difference":0.1,"moving_time":169,"split":8,"average_speed":5.96,"average_grade_adjusted_speed":null,"average_heartrate":127.02958579881657,"pace_zone":0},{"distance":986.7,"elapsed_time":513,"elevation_difference":-1.2,"moving_time":237,"split":9,"average_speed":4.16,"average_grade_adjusted_speed":null,"average_heartrate":108.81856540084388,"pace_zone":0},{"distance":988.9,"elapsed_time":194,"elevation_difference":1.1,"moving_time":194,"split":10,"average_speed":5.1,"average_grade_adjusted_speed":null,"average_heartrate":111.07731958762886,"pace_zone":0},{"distance":1033.8,"elapsed_time":216,"elevation_difference":1.7,"moving_time":216,"split":11,"average_speed":4.79,"average_grade_adjusted_speed":null,"average_heartrate":107.93981481481481,"pace_zone":0},{"distance":975.3,"elapsed_time":190,"elevation_difference":0.1,"moving_time":190,"split":12,"average_speed":5.13,"average_grade_adjusted_speed":null,"average_heartrate":108.28947368421052,"pace_zone":0},{"distance":1020.7,"elapsed_time":200,"elevation_difference":-0.6,"moving_time":200,"split":13,"average_speed":5.1,"average_grade_adjusted_speed":null,"average_heartrate":110.795,"pace_zone":0},{"distance":1002.4,"elapsed_time":188,"elevation_difference":0.2,"moving_time":188,"split":14,"average_speed":5.33,"average_grade_adjusted_speed":null,"average_heartrate":107.6063829787234,"pace_zone":0},{"distance":967.7,"elapsed_time":166,"elevation_difference":-0.6,"moving_time":166,"split":15,"average_speed":5.83,"average_grade_adjusted_speed":null,"average_heartrate":109.355421686747,"pace_zone":0},{"distance":1014.6,"elapsed_time":189,"elevation_difference":-0.1,"moving_time":189,"split":16,"average_speed":5.37,"average_grade_adjusted_speed":null,"average_heartrate":110.65079365079364,"pace_zone":0},{"distance":993,"elapsed_time":1721,"elevation_difference":0.1,"moving_time":216,"split":17,"average_speed":4.6,"average_grade_adjusted_speed":null,"average_heartrate":110.92592592592592,"pace_zone":0},{"distance":1006.7,"elapsed_time":207,"elevation_difference":0.9,"moving_time":207,"split":18,"average_speed":4.86,"average_grade_adjusted_speed":null,"average_heartrate":117.3913043478261,"pace_zone":0},{"distance":1003.8,"elapsed_time":193,"elevation_difference":1.2,"moving_time":193,"split":19,"average_speed":5.2,"average_grade_adjusted_speed":null,"average_heartrate":114.85492227979275,"pace_zone":0},{"distance":981.8,"elapsed_time":183,"elevation_difference":-0.3,"moving_time":183,"split":20,"average_speed":5.37,"average_grade_adjusted_speed":null,"average_heartrate":109.24590163934427,"pace_zone":0},{"distance":1011.9,"elapsed_time":230,"elevation_difference":-4.2,"moving_time":230,"split":21,"average_speed":4.4,"average_grade_adjusted_speed":null,"average_heartrate":104.7688888888889,"pace_zone":0},{"distance":148.4,"elapsed_time":29,"elevation_difference":1,"moving_time":29,"split":22,"average_speed":5.12,"average_grade_adjusted_speed":null,"average_heartrate":102.44827586206897,"pace_zone":0}],"splits_standard":[{"distance":1618.4,"elapsed_time":304,"elevation_difference":-1.8,"moving_time":304,"split":1,"average_speed":5.32,"average_grade_adjusted_speed":null,"average_heartrate":114.32236842105263,"pace_zone":0},{"distance":1608,"elapsed_time":310,"elevation_difference":1.7,"moving_time":310,"split":2,"average_speed":5.19,"average_grade_adjusted_speed":null,"average_heartrate":119.56451612903226,"pace_zone":0},{"distance":1629.8,"elapsed_time":309,"elevation_difference":1.5,"moving_time":309,"split":3,"average_speed":5.27,"average_grade_adjusted_speed":null,"average_heartrate":120.84142394822007,"pace_zone":0},{"distance":1594.9,"elapsed_time":297,"elevation_difference":-1,"moving_time":297,"split":4,"average_speed":5.37,"average_grade_adjusted_speed":null,"average_heartrate":121.05723905723906,"pace_zone":0},{"distance":1607.6,"elapsed_time":267,"elevation_difference":-4.2,"moving_time":267,"split":5,"average_speed":6.02,"average_grade_adjusted_speed":null,"average_heartrate":124.65917602996255,"pace_zone":0},{"distance":1628,"elapsed_time":639,"elevation_difference":-0.9,"moving_time":363,"split":6,"average_speed":4.48,"average_grade_adjusted_speed":null,"average_heartrate":109.47658402203857,"pace_zone":0},{"distance":1600.2,"elapsed_time":328,"elevation_difference":2.9,"moving_time":328,"split":7,"average_speed":4.88,"average_grade_adjusted_speed":null,"average_heartrate":108.5,"pace_zone":0},{"distance":1600.4,"elapsed_time":313,"elevation_difference":-0.6,"moving_time":313,"split":8,"average_speed":5.11,"average_grade_adjusted_speed":null,"average_heartrate":109.79552715654953,"pace_zone":0},{"distance":1604.4,"elapsed_time":293,"elevation_difference":-0.5,"moving_time":293,"split":9,"average_speed":5.48,"average_grade_adjusted_speed":null,"average_heartrate":107.98293515358361,"pace_zone":0},{"distance":1635.8,"elapsed_time":301,"elevation_difference":-0.6,"moving_time":301,"split":10,"average_speed":5.43,"average_grade_adjusted_speed":null,"average_heartrate":110.65448504983388,"pace_zone":0},{"distance":1578.6,"elapsed_time":1842,"elevation_difference":1.1,"moving_time":337,"split":11,"average_speed":4.68,"average_grade_adjusted_speed":null,"average_heartrate":113.90801186943621,"pace_zone":0},{"distance":1621,"elapsed_time":321,"elevation_difference":2.1,"moving_time":321,"split":12,"average_speed":5.05,"average_grade_adjusted_speed":null,"average_heartrate":113.5576323987539,"pace_zone":0},{"distance":1608.2,"elapsed_time":324,"elevation_difference":-4.7,"moving_time":324,"split":13,"average_speed":4.96,"average_grade_adjusted_speed":null,"average_heartrate":107.43260188087774,"pace_zone":0},{"distance":227.4,"elapsed_time":53,"elevation_difference":0.6,"moving_time":53,"split":14,"average_speed":4.29,"average_grade_adjusted_speed":null,"average_heartrate":99.86792452830188,"pace_zone":0}],"laps":[{"id":12381136552,"resource_state":2,"name":"Lap 1","activity":{"id":3757329634,"resource_state":1},"athlete":{"id":42223740,"resource_state":1},"elapsed_time":952,"moving_time":952,"start_date":"2020-07-13T16:15:00Z","start_date_local":"2020-07-13T18:15:00Z","distance":5000,"start_index":0,"end_index":289,"total_elevation_gain":86,"average_speed":5.25,"max_speed":7.7,"device_watts":false,"average_heartrate":118.3,"max_heartrate":129,"lap_index":1,"split":1},{"id":12381136554,"resource_state":2,"name":"Lap 2","activity":{"id":3757329634,"resource_state":1},"athlete":{"id":42223740,"resource_state":1},"elapsed_time":1235,"moving_time":959,"start_date":"2020-07-13T16:31:02Z","start_date_local":"2020-07-13T18:31:02Z","distance":5000,"start_index":290,"end_index":548,"total_elevation_gain":47,"average_speed":5.21,"max_speed":7.6,"device_watts":false,"average_heartrate":117.1,"max_heartrate":137,"lap_index":2,"split":2},{"id":12381136556,"resource_state":2,"name":"Lap 3","activity":{"id":3757329634,"resource_state":1},"athlete":{"id":42223740,"resource_state":1},"elapsed_time":960,"moving_time":960,"start_date":"2020-07-13T16:51:31Z","start_date_local":"2020-07-13T18:51:31Z","distance":5000,"start_index":549,"end_index":726,"total_elevation_gain":26,"average_speed":5.21,"max_speed":7,"device_watts":false,"average_heartrate":108.8,"max_heartrate":119,"lap_index":3,"split":3},{"id":12381136558,"resource_state":2,"name":"Lap 4","activity":{"id":3757329634,"resource_state":1},"athlete":{"id":42223740,"resource_state":1},"elapsed_time":2492,"moving_time":987,"start_date":"2020-07-13T17:07:35Z","start_date_local":"2020-07-13T19:07:35Z","distance":5000,"start_index":727,"end_index":950,"total_elevation_gain":40,"average_speed":5.07,"max_speed":7.1,"device_watts":false,"average_heartrate":112.7,"max_heartrate":124,"lap_index":4,"split":4},{"id":12381136562,"resource_state":2,"name":"Lap 5","activity":{"id":3757329634,"resource_state":1},"athlete":{"id":42223740,"resource_state":1},"elapsed_time":258,"moving_time":258,"start_date":"2020-07-13T17:49:03Z","start_date_local":"2020-07-13T19:49:03Z","distance":1162.68,"start_index":951,"end_index":1020,"total_elevation_gain":3,"average_speed":4.51,"max_speed":6.6,"device_watts":false,"average_heartrate":104.5,"max_heartrate":116,"lap_index":5,"split":5}],"photos":{"primary":null,"count":0},"stats_visibility":[{"type":"heart_rate","visibility":"everyone"},{"type":"pace","visibility":"everyone"},{"type":"power","visibility":"everyone"},{"type":"speed","visibility":"everyone"},{"type":"calories","visibility":"everyone"}],"hide_from_home":false,"device_name":"Garmin Forerunner 245","embed_token":"a569a82f797dd1c45c297036b8e15704adb99726","available_zones":[]}