{"resource_state":3,"athlete":{"id":42223740,"resource_state":1},"name":"Course à pied le midi","distance":11006.5,"moving_time":3397,"elapsed_time":3397,"total_elevation_gain":80.8,"type":"Run","sport_type":"Run","workout_type":null,"id":4785166806,"start_date":"2021-02-14T10:33:49Z","start_date_local":"2021-02-14T11:33:49Z","timezone":"(GMT+01:00) Europe/Paris","utc_offset":3600,"location_city":null,"location_state":null,"location_country":"France","achievement_count":8,"kudos_count":2,"comment_count":0,"athlete_count":1,"photo_count":0,"map":{"id":"a4785166806","polyline":"g|`eHf|pIE?W`@IBi@KcCM_BCc@Ha@Xg@n@q@dDEf@OJ[f@OA_@UiAe@CC_@Eg@Sy@aAq@_@eA_@i@a@YO_@B_@OYe@eAcAsA[cBWu@Dc@GWQ[Ia@Ey@@e@HGHAHXj@D|@FzCP~CAf@OhDN~A^NdBlA|ClB\\^^X`@R~AbA|AdBpAzBhBtCf@v@TKtAcArBmBHH^z@`@l@\\f@z@bAjBhDRv@p@nDJt@AnAKr@k@rBk@lAQt@Wh@m@l@Yl@gApE}@hCYdAw@|BaA~Da@d@_@^a@j@GLIf@l@fCpBpFBLEJa@ViA^c@Zy@x@G`@^~@h@`Bf@lBPjA@~@R~AAt@OlB@VRTd@TJP?PMZ{@`BKb@LXb@n@Pf@g@nFCbA@PJb@Cx@c@jHKb@?Bn@Lf@Br@Pn@\\b@Nf@JhCZzCHfAP\\VBP?Rq@`Bu@|AOz@AZDBZ?~G{@jBQhAId@?|@BPOH}@FoAFUHElAGPElC}@b@GjA\\z@`@t@Z`Bh@r@Pp@Df@RDEPuAFy@@y@Hu@LcBHKj@@rACd@GzB_DZa@ROb@Hb@FFIRcDRwEAy@UoAC[BAHDP\\HHXH~EnAf@P|D^v@L^CBEBW@{@LiD?_BFy@^}@^gB^_DFy@EyEBy@\\aDDyCHu@P{@`@uDHQ`AQh@Qb@SLMXm@Nw@ZkAXs@Tc@l@aA^g@Zk@Vo@@UdA_Ev@gDGYg@oA_ByBqAgCgByBe@_AQ}@Qg@a@w@Uo@KMUe@CAE@SRwAxCQVWDk@BO?e@Kq@o@a@WE?_Bt@g@A_AOqDa@yAIo@?qAT}Eh@c@HKBQLB`@CHE@mANq@Pe@FIEKSYkAWq@[[mCDCCISaAcJKs@G]Wi@q@Aq@Bg@Ay@KKBABCL?bAKn@eCtJQh@GFa@GOMg@{@OO[m@u@yBW}@W_@Oe@e@q@k@YY]Dm@GAYJWb@GBKEm@{AiCmFm@]Ys@s@yAI_@@ENO`@[j@[^_@Tw@AeA[m@a@e@u@iA_@WE?g@Pc@XCHCr@Tj@\\`@lAzCLJD?RC`@SRUNq@@u@AKQg@o@u@y@mAKM]?}@d@Sr@Yn@MJICe@}@QWUAUZWGg@]g@WQ_@J{@","resource_state":3,"summary_polyline":"g|`eHf|pIE?W`@IBi@KcCM_BCc@Ha@Xg@n@q@dDEf@OJ[f@OA_@UmAi@_@Eg@Sy@aAq@_@eA_@i@a@YO_@B_@OYe@eAcAsA[cBWu@Dc@GWQ}@Oy@@e@HGHAHXj@D|@FzCP~CAf@OhDN~A^NdBlA|ClB\\^^X`@R~AbA|AdBpAzBhBtCf@v@TKtAcArBmBHH^z@`@l@\\f@z@bAjBhDRv@p@nDJt@AnAKr@k@rBk@lAQt@Wh@m@l@Yl@gApE}@hCYdAw@|BaA~Da@d@_@^a@j@GLIf@l@fCpBpFBLEJa@ViA^c@Zy@x@G`@^~@h@`Bf@lBPjA@~@R~AAt@OlB@VRTd@TJP?PMZ{@`BKb@LXb@n@Pf@g@nFCbA@PJb@Cx@c@jHKb@?Bn@Lf@Br@Pn@\\b@Nf@JhCZzCHfAP\\VBP?Rq@`Bs@vAOx@Cb@DBZ?~G{@jBQhAIbBBPOH}@FoAFUHElAGPElC}@b@GjA\\pB|@`Bh@r@Pp@Df@RDEPuAFy@@y@Hu@LcBHKj@@rACd@GzB_DZa@ROfAPFIRcDRwEAy@UoAC[BAHDP\\HHXH~EnAf@P|D^v@L^CBEBW@{@LiD?_BFy@^}@^gB^_DFy@EyEBy@\\aDDyCHu@P{@`@uDHQ`AQh@Qb@SLMXm@Nw@ZkAXs@Tc@l@aA^g@Zk@Vo@@UdA_Ev@gDGYg@oA_ByBqAgCgByBe@_AQ}@Qg@a@w@Uo@KMUe@CAE@SRwAxCQVWDk@Bu@Kq@o@a@WeBt@g@AqFq@yAIo@?qATaGr@]PB`@CHE@mANq@Pe@FIEKSYkAWq@[[mCDCCISaAcJKs@G]Wi@q@Aq@Bg@Ay@KKBABCL?bAKn@eCtJQh@GFa@GOMg@{@OO[m@u@yBW}@W_@Oe@e@q@k@YY]Dm@GAYJWb@GBKEm@{AiCmFm@]Ys@s@yAI_@@ENO`@[j@[^_@Tw@AeA[m@a@e@u@iA_@Wm@Pc@XCHCr@Tj@\\`@lAzCLJD?RC`@SRUNq@@u@AKQg@o@u@y@mAKM]?}@d@Sr@Yn@MJICe@}@QWUAUZWGoAu@Q_@J{@"},"trainer":false,"commute":false,"manual":false,"private":false,"visibility":"everyone","flagged":false,"gear_id":null,"start_latlng":[48.178769,-1.730117],"end_latlng":[48.182179,-1.731683],"average_speed":3.24,"max_speed":4.4,"average_cadence":87.3,"has_heartrate":true,"average_heartrate":168.7,"max_heartrate":188,"heartrate_opt_out":false,"display_hide_heartrate_option":true,"elev_high":87.1,"elev_low":47.1,"upload_id":5106343977,"upload_id_str":"5106343977","external_id":"garmin_push_6270099926","from_accepted_tag":false,"pr_count":1,"total_photo_count":0,"has_kudoed":false,"description":null,"calories":840,"perceived_exertion":null,"prefer_perceived_exertion":null,"segment_efforts":[{"id":2796000359937957400,"resource_state":2,"name":"Du bourg vers le Bas Plessis","activity":{"id":4785166806,"resource_state":1},"athlete":{"id":42223740,"resource_state":1},"elapsed_time":88,"moving_time":88,"start_date":"2021-02-14T10:44:06Z","start_date_local":"2021-02-14T11:44:06Z","distance":305.3,"start_index":149,"end_index":168,"average_cadence":85.2,"device_watts":false,"average_heartrate":166,"max_heartrate":170,"segment":{"id":23464843,"resource_state":2,"name":"Du bourg vers le Bas Plessis","activity_type":"Run","distance":305.3,"average_grade":-0.6,"maximum_grade":-0.2,"elevation_high":73.7,"elevation_low":72,"start_latlng":[48.181273,-1.736353],"end_latlng":[48.17951,-1.739409],"elevation_profile":null,"climb_category":0,"city":"La Chapelle-des-Fougeretz","state":"Bretagne","country":"France","private":false,"hazardous":false,"starred":false},"pr_rank":2,"achievements":[{"type_id":3,"type":"pr","rank":2}],"hidden":false},{"id":2796000359937017300,"resource_state":2,"name":"Pop corn à la chapelle","activity":{"id":4785166806,"resource_state":1},"athlete":{"id":42223740,"resource_state":1},"elapsed_time":135,"moving_time":135,"start_date":"2021-02-14T10:46:38Z","start_date_local":"2021-02-14T11:46:38Z","distance":439.5,"start_index":183,"end_index":212,"average_cadence":85.2,"device_watts":false,"average_heartrate":167.4,"max_heartrate":172,"segment":{"id":24168816,"resource_state":2,"name":"Pop corn à la chapelle","activity_type":"Run","distance":439.5,"average_grade":-0.6,"maximum_grade":5.7,"elevation_high":89.4,"elevation_low":83.8,"start_latlng":[48.180337,-1.741757],"end_latlng":[48.182574,-1.746466],"elevation_profile":null,"climb_category":0,"city":"La Chapelle-des-Fougeretz","state":"Bretagne","country":"France","private":false,"hazardous":false,"starred":false},"pr_rank":2,"achievements":[{"type_id":3,"type":"pr","rank":2}],"hidden":false},{"id":2796000359935600000,"resource_state":2,"name":"Chenetay - Les Pruniers","activity":{"id":4785166806,"resource_state":1},"athlete":{"id":42223740,"resource_state":1},"elapsed_time":623,"moving_time":623,"start_date":"2021-02-14T10:46:45Z","start_date_local":"2021-02-14T11:46:45Z","distance":2003.5,"start_index":185,"end_index":324,"average_cadence":87.1,"device_watts":false,"average_heartrate":168.6,"max_heartrate":174,"segment":{"id":12172160,"resource_state":2,"name":"Chenetay - Les Pruniers","activity_type":"Run","distance":2003.5,"average_grade":-0.2,"maximum_grade":4.2,"elevation_high":79.2,"elevation_low":66.8,"start_latlng":[48.180524,-1.742008],"end_latlng":[48.179545,-1.760837],"elevation_profile":null,"climb_category":0,"city":"La Chapelle-des-Fougeretz","state":"Bretagne","country":"France","private":false,"hazardous":false,"starred":false},"pr_rank":2,"achievements":[{"type_id":3,"type":"pr","rank":2}],"hidden":false},{"id":2796000359937883600,"resource_state":2,"name":"vers le verger","activity":{"id":4785166806,"resource_state":1},"athlete":{"id":42223740,"resource_state":1},"elapsed_time":267,"moving_time":267,"start_date":"2021-02-14T10:52:42Z","start_date_local":"2021-02-14T11:52:42Z","distance":856,"start_index":265,"end_index":325,"average_cadence":87.7,"device_watts":false,"average_heartrate":171.7,"max_heartrate":174,"segment":{"id":24168989,"resource_state":2,"name":"vers le verger","activity_type":"Run","distance":856,"average_grade":0.8,"maximum_grade":4.9,"elevation_high":87.4,"elevation_low":78.4,"start_latlng":[48.182167,-1.754345],"end_latlng":[48.17961,-1.760999],"elevation_profile":null,"climb_category":0,"city":"La Chapelle-des-Fougeretz","state":"Bretagne","country":"France","private":false,"hazardous":false,"starred":false},"pr_rank":2,"achievements":[{"type_id":3,"type":"pr","rank":2}],"hidden":false},{"id":2796000359938420000,"resource_state":2,"name":"la derre - maison neuve","activity":{"id":4785166806,"resource_state":1},"athlete":{"id":42223740,"resource_state":1},"elapsed_time":133,"moving_time":133,"start_date":"2021-02-14T11:01:27Z","start_date_local":"2021-02-14T12:01:27Z","distance":396.5,"start_index":381,"end_index":407,"average_cadence":88.2,"device_watts":false,"average_heartrate":165.3,"max_heartrate":170,"segment":{"id":24169042,"resource_state":2,"name":"la derre - maison neuve","activity_type":"Run","distance":396.5,"average_grade":-2.4,"maximum_grade":0,"elevation_high":74.2,"elevation_low":64.8,"start_latlng":[48.172706,-1.760214],"end_latlng":[48.170337,-1.757366],"elevation_profile":null,"climb_category":0,"city":"La Chapelle-des-Fougeretz","state":"Bretagne","country":"France","private":false,"hazardous":false,"starred":false},"pr_rank":3,"achievements":[{"type_id":3,"type":"pr","rank":3}],"hidden":false},{"id":2796000359936272000,"resource_state":2,"name":"Faux-plat de La Noé","activity":{"id":4785166806,"resource_state":1},"athlete":{"id":42223740,"resource_state":1},"elapsed_time":152,"moving_time":152,"start_date":"2021-02-14T11:07:58Z","start_date_local":"2021-02-14T12:07:58Z","distance":475.9,"start_index":466,"end_index":498,"average_cadence":89,"device_watts":false,"average_heartrate":171.6,"max_heartrate":176,"segment":{"id":9560708,"resource_state":2,"name":"Faux-plat de La Noé","activity_type":"Run","distance":475.9,"average_grade":3.2,"maximum_grade":5,"elevation_high":61,"elevation_low":45.5,"start_latlng":[48.166675,-1.752183],"end_latlng":[48.165357,-1.746753],"elevation_profile":null,"climb_category":0,"city":"La Chapelle-des-Fougeretz","state":"Bretagne","country":"France","private":false,"hazardous":false,"starred":false},"pr_rank":null,"achievements":[],"hidden":false},{"id":2796000359935560000,"resource_state":2,"name":"la drille","activity":{"id":4785166806,"resource_state":1},"athlete":{"id":42223740,"resource_state":1},"elapsed_time":197,"moving_time":197,"start_date":"2021-02-14T11:11:21Z","start_date_local":"2021-02-14T12:11:21Z","distance":640.1,"start_index":510,"end_index":551,"average_cadence":88.2,"device_watts":false,"average_heartrate":172.8,"max_heartrate":181,"segment":{"id":24168441,"resource_state":2,"name":"la drille","activity_type":"Run","distance":640.1,"average_grade":0.2,"maximum_grade":5,"elevation_high":67.8,"elevation_low":61.6,"start_latlng":[48.16444,-1.745151],"end_latlng":[48.165735,-1.738614],"elevation_profile":null,"climb_category":0,"city":"La Chapelle-des-Fougeretz","state":"Bretagne","country":"France","private":false,"hazardous":false,"starred":false},"pr_rank":2,"achievements":[{"type_id":3,"type":"pr","rank":2}],"hidden":false},{"id":2796000359935258000,"resource_state":2,"name":"La Senestrais","activity":{"id":4785166806,"resource_state":1},"athlete":{"id":42223740,"resource_state":1},"elapsed_time":191,"moving_time":191,"start_date":"2021-02-14T11:15:21Z","start_date_local":"2021-02-14T12:15:21Z","distance":599.4,"start_index":562,"end_index":603,"average_cadence":89.1,"device_watts":false,"average_heartrate":177.9,"max_heartrate":180,"segment":{"id":25627223,"resource_state":2,"name":"La Senestrais","activity_type":"Run","distance":599.4,"average_grade":1.9,"maximum_grade":4,"elevation_high":74.4,"elevation_low":63.1,"start_latlng":[48.166622,-1.739583],"end_latlng":[48.171875,-1.739495],"elevation_profile":null,"climb_category":0,"city":"La Chapelle-des-Fougeretz","state":"Bretagne","country":"France","private":false,"hazardous":false,"starred":false},"pr_rank":2,"achievements":[{"type_id":3,"type":"pr","rank":2}],"hidden":false},{"id":2796000359935369700,"resource_state":2,"name":"ZA La chapelle","activity":{"id":4785166806,"resource_state":1},"athlete":{"id":42223740,"resource_state":1},"elapsed_time":219,"moving_time":219,"start_date":"2021-02-14T11:19:05Z","start_date_local":"2021-02-14T12:19:05Z","distance":696.7,"start_index":615,"end_index":667,"average_cadence":88.5,"device_watts":false,"average_heartrate":176,"max_heartrate":181,"segment":{"id":10886777,"resource_state":2,"name":"ZA La chapelle","activity_type":"Run","distance":696.7,"average_grade":-1.1,"maximum_grade":4.6,"elevation_high":74.1,"elevation_low":62.8,"start_latlng":[48.172767,-1.739907],"end_latlng":[48.176576,-1.739223],"elevation_profile":null,"climb_category":0,"city":"La Chapelle-des-Fougeretz","state":"Bretagne","country":"France","private":false,"hazardous":false,"starred":false},"pr_rank":null,"achievements":[],"hidden":false},{"id":2796000359938313700,"resource_state":2,"name":"ça gicle !","activity":{"id":4785166806,"resource_state":1},"athlete":{"id":42223740,"resource_state":1},"elapsed_time":72,"moving_time":72,"start_date":"2021-02-14T11:22:52Z","start_date_local":"2021-02-14T12:22:52Z","distance":247.5,"start_index":669,"end_index":686,"average_cadence":88.4,"device_watts":false,"average_heartrate":175.8,"max_heartrate":178,"segment":{"id":24168626,"resource_state":2,"name":"ça gicle !","activity_type":"Run","distance":247.5,"average_grade":1.7,"maximum_grade":12.2,"elevation_high":76.6,"elevation_low":71.4,"start_latlng":[48.176734,-1.739352],"end_latlng":[48.17824,-1.737021],"elevation_profile":null,"climb_category":0,"city":"La Chapelle-des-Fougeretz","state":"Bretagne","country":"France","private":false,"hazardous":false,"starred":false},"pr_rank":1,"achievements":[{"type_id":3,"type":"pr","rank":1}],"hidden":false},{"id":2796000359935627000,"resource_state":2,"name":"Le moulin Neuf","activity":{"id":4785166806,"resource_state":1},"athlete":{"id":42223740,"resource_state":1},"elapsed_time":60,"moving_time":60,"start_date":"2021-02-14T11:24:23Z","start_date_local":"2021-02-14T12:24:23Z","distance":186.8,"start_index":693,"end_index":708,"average_cadence":88.2,"device_watts":false,"average_heartrate":176.3,"max_heartrate":180,"segment":{"id":20845233,"resource_state":2,"name":"Le moulin Neuf","activity_type":"Run","distance":186.8,"average_grade":0.2,"maximum_grade":2.5,"elevation_high":67.5,"elevation_low":66.4,"start_latlng":[48.178546,-1.736763],"end_latlng":[48.179692,-1.73518],"elevation_profile":null,"climb_category":0,"city":"La Chapelle-des-Fougeretz","state":"Bretagne","country":"France","private":false,"hazardous":false,"starred":false},"pr_rank":null,"achievements":[],"hidden":false},{"id":2796000359938374000,"resource_state":2,"name":"Tour étang La Chapelle","activity":{"id":4785166806,"resource_state":1},"athlete":{"id":42223740,"resource_state":1},"elapsed_time":106,"moving_time":106,"start_date":"2021-02-14T11:26:46Z","start_date_local":"2021-02-14T12:26:46Z","distance":415.7,"start_index":729,"end_index":756,"average_cadence":89.5,"device_watts":false,"average_heartrate":186,"max_heartrate":188,"segment":{"id":13515789,"resource_state":2,"name":"Tour étang La Chapelle","activity_type":"Run","distance":415.7,"average_grade":-0.1,"maximum_grade":5.4,"elevation_high":74.5,"elevation_low":69.6,"start_latlng":[48.179799,-1.732678],"end_latlng":[48.179873,-1.732572],"elevation_profile":null,"climb_category":0,"city":"La Chapelle-des-Fougeretz","state":"Bretagne","country":"France","private":false,"hazardous":false,"starred":true},"pr_rank":null,"achievements":[],"hidden":false}],"splits_metric":[{"distance":1000.4,"elapsed_time":316,"elevation_difference":-3.5,"moving_time":316,"split":1,"average_speed":3.17,"average_grade_adjusted_speed":3.16,"average_heartrate":142.8920634920635,"pace_zone":0},{"distance":1002,"elapsed_time":309,"elevation_difference":-9.2,"moving_time":309,"split":2,"average_speed":3.24,"average_grade_adjusted_speed":3.19,"average_heartrate":163.7799352750809,"pace_zone":0},{"distance":999.8,"elapsed_time":303,"elevation_difference":-0.8,"moving_time":303,"split":3,"average_speed":3.3,"average_grade_adjusted_speed":3.33,"average_heartrate":166.58415841584159,"pace_zone":0},{"distance":998.9,"elapsed_time":309,"elevation_difference":5.3,"moving_time":309,"split":4,"average_speed":3.23,"average_grade_adjusted_speed":3.3,"average_heartrate":168.3527508090615,"pace_zone":0},{"distance":1000.4,"elapsed_time":309,"elevation_difference":-4.9,"moving_time":309,"split":5,"average_speed":3.24,"average_grade_adjusted_speed":3.21,"average_heartrate":169.7799352750809,"pace_zone":0},{"distance":1001.1,"elapsed_time":318,"elevation_difference":-14.8,"moving_time":318,"split":6,"average_speed":3.15,"average_grade_adjusted_speed":3.06,"average_heartrate":167.57232704402514,"pace_zone":0},{"distance":1000,"elapsed_time":312,"elevation_difference":-2.4,"moving_time":312,"split":7,"average_speed":3.21,"average_grade_adjusted_speed":3.21,"average_heartrate":169.34294871794873,"pace_zone":0},{"distance":998.7,"elapsed_time":316,"elevation_difference":8.5,"moving_time":316,"split":8,"average_speed":3.16,"average_grade_adjusted_speed":3.24,"average_heartrate":174.18354430379748,"pace_zone":0},{"distance":1001,"elapsed_time":312,"elevation_difference":8.5,"moving_time":312,"split":9,"average_speed":3.21,"average_grade_adjusted_speed":3.3,"average_heartrate":177.19871794871796,"pace_zone":0},{"distance":999.1,"elapsed_time":300,"elevation_difference":-1.6,"moving_time":300,"split":10,"average_speed":3.33,"average_grade_adjusted_speed":3.34,"average_heartrate":175.94666666666666,"pace_zone":0},{"distance":1001.9,"elapsed_time":292,"elevation_difference":3.7,"moving_time":292,"split":11,"average_speed":3.43,"average_grade_adjusted_speed":3.47,"average_heartrate":181.62328767123287,"pace_zone":0},{"distance":3.2,"elapsed_time":1,"elevation_difference":0,"moving_time":1,"split":12,"average_speed":3.2,"average_grade_adjusted_speed":3.1,"average_heartrate":179,"pace_zone":0}],"splits_standard":[{"distance":1614.7,"elapsed_time":510,"elevation_difference":-1.3,"moving_time":510,"split":1,"average_speed":3.17,"average_grade_adjusted_speed":3.18,"average_heartrate":151.10609037328095,"pace_zone":0},{"distance":1608.6,"elapsed_time":485,"elevation_difference":-14.3,"moving_time":485,"split":2,"average_speed":3.32,"average_grade_adjusted_speed":3.28,"average_heartrate":165.44948453608248,"pace_zone":0},{"distance":1615.5,"elapsed_time":502,"elevation_difference":5.3,"moving_time":502,"split":3,"average_speed":3.22,"average_grade_adjusted_speed":3.26,"average_heartrate":169.50796812749005,"pace_zone":0},{"distance":1621.1,"elapsed_time":505,"elevation_difference":-26.5,"moving_time":505,"split":4,"average_speed":3.21,"average_grade_adjusted_speed":3.11,"average_heartrate":168.23168316831683,"pace_zone":0},{"distance":1597.2,"elapsed_time":508,"elevation_difference":15.4,"moving_time":508,"split":5,"average_speed":3.14,"average_grade_adjusted_speed":3.23,"average_heartrate":172.66338582677164,"pace_zone":0},{"distance":1610.8,"elapsed_time":490,"elevation_difference":4.8,"moving_time":490,"split":6,"average_speed":3.29,"average_grade_adjusted_speed":3.35,"average_heartrate":176.5387755102041,"pace_zone":0},{"distance":1338.6,"elapsed_time":397,"elevation_difference":5.4,"moving_time":397,"split":7,"average_speed":3.37,"average_grade_adjusted_speed":3.41,"average_heartrate":180.35768261964736,"pace_zone":0}],"laps":[{"id":15643992859,"resource_state":2,"name":"Lap 1","activity":{"id":4785166806,"resource_state":1},"athlete":{"id":42223740,"resource_state":1},"elapsed_time":316,"moving_time":316,"start_date":"2021-02-14T10:33:49Z","start_date_local":"2021-02-14T11:33:49Z","distance":1000,"start_index":0,"end_index":81,"total_elevation_gain":16,"average_speed":3.16,"max_speed":3.9,"average_cadence":84.4,"device_watts":false,"average_heartrate":142.9,"max_heartrate":164,"lap_index":1,"split":1,"pace_zone":0},{"id":15643992870,"resource_state":2,"name":"Lap 2","activity":{"id":4785166806,"resource_state":1},"athlete":{"id":42223740,"resource_state":1},"elapsed_time":308,"moving_time":308,"start_date":"2021-02-14T10:39:07Z","start_date_local":"2021-02-14T11:39:07Z","distance":1000,"start_index":82,"end_index":151,"total_elevation_gain":15,"average_speed":3.25,"max_speed":3.7,"average_cadence":84.7,"device_watts":false,"average_heartrate":163.8,"max_heartrate":167,"lap_index":2,"split":2,"pace_zone":0},{"id":15643992879,"resource_state":2,"name":"Lap 3","activity":{"id":4785166806,"resource_state":1},"athlete":{"id":42223740,"resource_state":1},"elapsed_time":303,"moving_time":303,"start_date":"2021-02-14T10:44:15Z","start_date_local":"2021-02-14T11:44:15Z","distance":1000,"start_index":152,"end_index":217,"total_elevation_gain":10,"average_speed":3.3,"max_speed":3.7,"average_cadence":85.5,"device_watts":false,"average_heartrate":166.6,"max_heartrate":172,"lap_index":3,"split":3,"pace_zone":0},{"id":15643992891,"resource_state":2,"name":"Lap 4","activity":{"id":4785166806,"resource_state":1},"athlete":{"id":42223740,"resource_state":1},"elapsed_time":309,"moving_time":309,"start_date":"2021-02-14T10:49:23Z","start_date_local":"2021-02-14T11:49:23Z","distance":1000,"start_index":218,"end_index":288,"total_elevation_gain":18,"average_speed":3.24,"max_speed":4,"average_cadence":87.7,"device_watts":false,"average_heartrate":168.5,"max_heartrate":173,"lap_index":4,"split":4,"pace_zone":0},{"id":15643992899,"resource_state":2,"name":"Lap 5","activity":{"id":4785166806,"resource_state":1},"athlete":{"id":42223740,"resource_state":1},"elapsed_time":309,"moving_time":309,"start_date":"2021-02-14T10:54:31Z","start_date_local":"2021-02-14T11:54:31Z","distance":1000,"start_index":289,"end_index":357,"total_elevation_gain":9,"average_speed":3.24,"max_speed":3.5,"average_cadence":87.7,"device_watts":false,"average_heartrate":169.7,"max_heartrate":174,"lap_index":5,"split":5,"pace_zone":0},{"id":15643992908,"resource_state":2,"name":"Lap 6","activity":{"id":4785166806,"resource_state":1},"athlete":{"id":42223740,"resource_state":1},"elapsed_time":317,"moving_time":317,"start_date":"2021-02-14T10:59:37Z","start_date_local":"2021-02-14T11:59:37Z","distance":1000,"start_index":358,"end_index":425,"total_elevation_gain":7,"average_speed":3.15,"max_speed":3.5,"average_cadence":88,"device_watts":false,"average_heartrate":167.6,"max_heartrate":173,"lap_index":6,"split":6,"pace_zone":0},{"id":15643992915,"resource_state":2,"name":"Lap 7","activity":{"id":4785166806,"resource_state":1},"athlete":{"id":42223740,"resource_state":1},"elapsed_time":311,"moving_time":311,"start_date":"2021-02-14T11:04:55Z","start_date_local":"2021-02-14T12:04:55Z","distance":1000,"start_index":426,"end_index":493,"total_elevation_gain":10,"average_speed":3.22,"max_speed":3.6,"average_cadence":88.6,"device_watts":false,"average_heartrate":169.3,"max_heartrate":173,"lap_index":7,"split":7,"pace_zone":0},{"id":15643992922,"resource_state":2,"name":"Lap 8","activity":{"id":4785166806,"resource_state":1},"athlete":{"id":42223740,"resource_state":1},"elapsed_time":316,"moving_time":316,"start_date":"2021-02-14T11:10:06Z","start_date_local":"2021-02-14T12:10:06Z","distance":1000,"start_index":494,"end_index":562,"total_elevation_gain":47,"average_speed":3.16,"max_speed":4.1,"average_cadence":88.1,"device_watts":false,"average_heartrate":174.2,"max_heartrate":181,"lap_index":8,"split":8,"pace_zone":0},{"id":15643992928,"resource_state":2,"name":"Lap 9","activity":{"id":4785166806,"resource_state":1},"athlete":{"id":42223740,"resource_state":1},"elapsed_time":311,"moving_time":311,"start_date":"2021-02-14T11:15:22Z","start_date_local":"2021-02-14T12:15:22Z","distance":1000,"start_index":563,"end_index":636,"total_elevation_gain":27,"average_speed":3.22,"max_speed":3.7,"average_cadence":88.9,"device_watts":false,"average_heartrate":177.2,"max_heartrate":180,"lap_index":9,"split":9,"pace_zone":0},{"id":15643992936,"resource_state":2,"name":"Lap 10","activity":{"id":4785166806,"resource_state":1},"athlete":{"id":42223740,"resource_state":1},"elapsed_time":300,"moving_time":300,"start_date":"2021-02-14T11:20:34Z","start_date_local":"2021-02-14T12:20:34Z","distance":1000,"start_index":637,"end_index":711,"total_elevation_gain":30,"average_speed":3.33,"max_speed":3.9,"average_cadence":88.2,"device_watts":false,"average_heartrate":176,"max_heartrate":181,"lap_index":10,"split":10,"pace_zone":0},{"id":15643992944,"resource_state":2,"name":"Lap 11","activity":{"id":4785166806,"resource_state":1},"athlete":{"id":42223740,"resource_state":1},"elapsed_time":291,"moving_time":291,"start_date":"2021-02-14T11:25:39Z","start_date_local":"2021-02-14T12:25:39Z","distance":1000,"start_index":712,"end_index":781,"total_elevation_gain":12,"average_speed":3.44,"max_speed":4.4,"average_cadence":88.6,"device_watts":false,"average_heartrate":181.7,"max_heartrate":188,"lap_index":11,"split":11,"pace_zone":0}],"best_efforts":[{"id":9968870940,"resource_state":2,"name":"400m","activity":{"id":4785166806,"resource_state":1},"athlete":{"id":42223740,"resource_state":1},"elapsed_time":98,"moving_time":99,"start_date":"2021-02-14T11:26:32Z","start_date_local":"2021-02-14T12:26:32Z","distance":400,"start_index":726,"end_index":751,"pr_rank":null,"achievements":[]},{"id":9968870947,"resource_state":2,"name":"1/2 mile","activity":{"id":4785166806,"resource_state":1},"athlete":{"id":42223740,"resource_state":1},"elapsed_time":224,"moving_time":225,"start_date":"2021-02-14T11:24:31Z","start_date_local":"2021-02-14T12:24:31Z","distance":805,"start_index":695,"end_index":752,"pr_rank":null,"achievements":[]},{"id":9968870952,"resource_state":2,"name":"1k","activity":{"id":4785166806,"resource_state":1},"athlete":{"id":42223740,"resource_state":1},"elapsed_time":286,"moving_time":287,"start_date":"2021-02-14T11:23:29Z","start_date_local":"2021-02-14T12:23:29Z","distance":1000,"start_index":679,"end_index":752,"pr_rank":null,"achievements":[]},{"id":9968870962,"resource_state":2,"name":"1 mile","activity":{"id":4785166806,"resource_state":1},"athlete":{"id":42223740,"resource_state":1},"elapsed_time":463,"moving_time":464,"start_date":"2021-02-14T11:20:33Z","start_date_local":"2021-02-14T12:20:33Z","distance":1609,"start_index":636,"end_index":753,"pr_rank":null,"achievements":[]},{"id":9968870971,"resource_state":2,"name":"2 mile","activity":{"id":4785166806,"resource_state":1},"athlete":{"id":42223740,"resource_state":1},"elapsed_time":964,"moving_time":968,"start_date":"2021-02-14T11:12:14Z","start_date_local":"2021-02-14T12:12:14Z","distance":3219,"start_index":521,"end_index":754,"pr_rank":null,"achievements":[]},{"id":9968870979,"resource_state":2,"name":"5k","activity":{"id":4785166806,"resource_state":1},"athlete":{"id":42223740,"resource_state":1},"elapsed_time":1526,"moving_time":1527,"start_date":"2021-02-14T11:03:01Z","start_date_local":"2021-02-14T12:03:01Z","distance":5000,"start_index":399,"end_index":755,"pr_rank":null,"achievements":[]},{"id":9968870987,"resource_state":2,"name":"10k","activity":{"id":4785166806,"resource_state":1},"athlete":{"id":42223740,"resource_state":1},"elapsed_time":3074,"moving_time":3075,"start_date":"2021-02-14T10:37:02Z","start_date_local":"2021-02-14T11:37:02Z","distance":10000,"start_index":52,"end_index":753,"pr_rank":null,"achievements":[]}],"photos":{"primary":null,"count":0},"stats_visibility":[{"type":"heart_rate","visibility":"everyone"},{"type":"pace","visibility":"everyone"},{"type":"power","visibility":"everyone"},{"type":"speed","visibility":"everyone"},{"type":"calories","visibility":"everyone"}],"hide_from_home":false,"device_name":"Garmin Forerunner 245","embed_token":"81c321ab30337b227857f654496134bb5d2edb11","similar_activities":{"effort_count":2,"average_speed":3.366991268382353,"min_average_speed":3.2400647630261994,"mid_average_speed":3.3704532691404183,"max_average_speed":3.511776136983714,"pr_rank":1,"frequency_milestone":null,"trend":{"speeds":[3.2400647630261994,3.3704532691404183],"current_activity_index":0,"min_speed":3.2400647630261994,"mid_speed":3.3704532691404183,"max_speed":3.511776136983714,"direction":0},"resource_state":2},"available_zones":[]}