{"resource_state":3,"athlete":{"id":42223740,"resource_state":1},"name":"Course à pied le midi","distance":3545,"moving_time":1488,"elapsed_time":1491,"total_elevation_gain":21.6,"type":"Run","sport_type":"Run","workout_type":0,"id":4854101189,"start_date":"2021-02-26T11:21:28Z","start_date_local":"2021-02-26T12:21:28Z","timezone":"(GMT+01:00) Europe/Paris","utc_offset":3600,"location_city":null,"location_state":null,"location_country":"France","achievement_count":0,"kudos_count":0,"comment_count":0,"athlete_count":1,"photo_count":0,"map":{"id":"a4854101189","polyline":"clg_HheuHFTCZ@FxAjAFf@Kx@MrAERkAjDSd@[d@?^PRd@Rr@f@Z\\TAR]b@Yd@ERX\\Lh@gA^YLGh@e@b@[b@W^c@\\]rAi@VCb@KVi@^iAPgAAG^mC?]Ag@Ka@?k@Iw@Ja@HGXInAEz@Sl@Al@i@\\SPc@VgARs@`@aAVaBFIHk@XWZONa@m@_BMw@Dm@A{AHq@Ls@Rk@@[I@w@xAy@tAWl@Ib@G`B@f@Hl@l@l@V`@TTERUD_@O[Ga@CWRW\\y@z@sAhAYj@[X]Ja@@[N[TW^O`@[n@Eh@@VBVNl@HJf@XZDTFP^Dl@Cj@_@dDYpAc@hAKJeAV}@b@UPYn@Yh@Uj@Gb@I|A@f@d@`Hb@nCIj@EFSL]KSk@Qm@i@wB]_CU{@[yAa@y@MKIYSIK?c@Z_@`@WCUUcBgAMMAYh@uAvAoEBm@X[","resource_state":3,"summary_polyline":"clg_HheuHFTCZ@FxAjAFf@Kx@MrAERkAjDSd@[d@?^PRd@Rr@f@Z\\TAR]b@Yd@ERX\\Lh@gA^YLGh@e@b@[b@W^c@\\]rAi@VCb@KVi@^iAPgAAG^mC?]Ag@Ka@?k@Iw@Ja@HGXInAEz@Sl@Al@i@\\SPc@VgARs@`@aAVaBFIHk@XWZONa@m@_BMw@Dm@A{AHq@Ls@Rk@@[I@w@xAy@tAWl@Ib@G`B@f@Hl@l@l@V`@TTERUD_@O[Ga@CWRW\\y@z@sAhAYj@[X]Ja@@[N[TW^O`@[n@Eh@@VBVNl@HJf@XZDTFP^Dl@Cj@_@dDYpAc@hAKJeAV}@b@UPYn@Yh@Uj@Gb@I|A@f@d@`Hb@nCIj@EFSL]KSk@Qm@i@wB]_CU{@[yAa@y@MKIYSIK?c@Z_@`@WCUUcBgAMMAYh@uAvAoEBm@X["},"trainer":false,"commute":false,"manual":false,"private":true,"visibility":"only_me","flagged":false,"gear_id":null,"start_latlng":[47.228985,-1.588209],"end_latlng":[47.228467,-1.589317],"average_speed":2.382,"max_speed":3.4,"average_cadence":77,"has_heartrate":true,"average_heartrate":158.5,"max_heartrate":174,"heartrate_opt_out":false,"display_hide_heartrate_option":true,"elev_high":35.2,"elev_low":12.1,"upload_id":5177901710,"upload_id_str":"5177901710","external_id":"garmin_push_6338299494","from_accepted_tag":false,"pr_count":0,"total_photo_count":0,"has_kudoed":false,"description":"","calories":318,"perceived_exertion":null,"prefer_perceived_exertion":false,"segment_efforts":[{"id":2800430567341057000,"resource_state":2,"name":"piscine-pont jules Cesar","activity":{"id":4854101189,"resource_state":1},"athlete":{"id":42223740,"resource_state":1},"elapsed_time":234,"moving_time":234,"start_date":"2021-02-26T11:26:01Z","start_date_local":"2021-02-26T12:26:01Z","distance":586.5,"start_index":71,"end_index":124,"average_cadence":77.5,"device_watts":false,"average_heartrate":157.1,"max_heartrate":174,"segment":{"id":7370509,"resource_state":2,"name":"piscine-pont jules Cesar","activity_type":"Run","distance":586.5,"average_grade":0.6,"maximum_grade":8,"elevation_high":23.6,"elevation_low":14.3,"start_latlng":[47.226213,-1.590309],"end_latlng":[47.223282,-1.585754],"elevation_profile":null,"climb_category":0,"city":"Nantes","state":"Pays de la Loire","country":"France","private":false,"hazardous":false,"starred":true},"pr_rank":null,"achievements":[],"hidden":false},{"id":2800430567342592000,"resource_state":2,"name":"passage à côté du stade jusqu'au terrain de tennis","activity":{"id":4854101189,"resource_state":1},"athlete":{"id":42223740,"resource_state":1},"elapsed_time":88,"moving_time":88,"start_date":"2021-02-26T11:39:43Z","start_date_local":"2021-02-26T12:39:43Z","distance":223.7,"start_index":246,"end_index":265,"average_cadence":77.4,"device_watts":false,"average_heartrate":167.8,"max_heartrate":169,"segment":{"id":20310261,"resource_state":2,"name":"passage à côté du stade jusqu'au terrain de tennis","activity_type":"Run","distance":223.7,"average_grade":-0.4,"maximum_grade":10,"elevation_high":15.6,"elevation_low":12.2,"start_latlng":[47.22684,-1.591364],"end_latlng":[47.226487,-1.594207],"elevation_profile":null,"climb_category":0,"city":"Nantes","state":"Pays de la Loire","country":"France","private":false,"hazardous":false,"starred":true},"pr_rank":null,"achievements":[],"hidden":false},{"id":2800430567344408600,"resource_state":2,"name":"chez moi","activity":{"id":4854101189,"resource_state":1},"athlete":{"id":42223740,"resource_state":1},"elapsed_time":122,"moving_time":122,"start_date":"2021-02-26T11:43:07Z","start_date_local":"2021-02-26T12:43:07Z","distance":238,"start_index":283,"end_index":307,"average_cadence":73.2,"device_watts":false,"average_heartrate":166.7,"max_heartrate":167,"segment":{"id":19642112,"resource_state":2,"name":"chez moi","activity_type":"Run","distance":238,"average_grade":6.7,"maximum_grade":19.6,"elevation_high":6,"elevation_low":-10.2,"start_latlng":[47.227738,-1.592083],"end_latlng":[47.229402,-1.591157],"elevation_profile":null,"climb_category":0,"city":null,"state":null,"country":null,"private":false,"hazardous":false,"starred":true},"pr_rank":null,"achievements":[],"hidden":false}],"splits_metric":[{"distance":1001.3,"elapsed_time":406,"elevation_difference":-21.3,"moving_time":406,"split":1,"average_speed":2.47,"average_grade_adjusted_speed":2.41,"average_heartrate":146.3233830845771,"pace_zone":0},{"distance":1005.3,"elapsed_time":417,"elevation_difference":2.3,"moving_time":414,"split":2,"average_speed":2.43,"average_grade_adjusted_speed":2.44,"average_heartrate":158.35011990407673,"pace_zone":0},{"distance":1000.5,"elapsed_time":409,"elevation_difference":-0.8,"moving_time":409,"split":3,"average_speed":2.45,"average_grade_adjusted_speed":2.45,"average_heartrate":165.72616136919316,"pace_zone":0},{"distance":538,"elapsed_time":260,"elevation_difference":10.1,"moving_time":260,"split":4,"average_speed":2.07,"average_grade_adjusted_speed":2.25,"average_heartrate":165.9653846153846,"pace_zone":0}],"splits_standard":[{"distance":1629.7,"elapsed_time":664,"elevation_difference":-22.1,"moving_time":661,"split":1,"average_speed":2.47,"average_grade_adjusted_speed":2.43,"average_heartrate":149.56969696969696,"pace_zone":0},{"distance":1591.8,"elapsed_time":673,"elevation_difference":4.7,"moving_time":673,"split":2,"average_speed":2.37,"average_grade_adjusted_speed":2.39,"average_heartrate":165.46508172362556,"pace_zone":0},{"distance":323.6,"elapsed_time":155,"elevation_difference":7.7,"moving_time":155,"split":3,"average_speed":2.09,"average_grade_adjusted_speed":2.33,"average_heartrate":165.89032258064515,"pace_zone":0}],"laps":[{"id":15864776352,"resource_state":2,"name":"Lap 1","activity":{"id":4854101189,"resource_state":1},"athlete":{"id":42223740,"resource_state":1},"elapsed_time":405,"moving_time":405,"start_date":"2021-02-26T11:21:28Z","start_date_local":"2021-02-26T12:21:28Z","distance":1000,"start_index":0,"end_index":99,"total_elevation_gain":30,"average_speed":2.47,"max_speed":3.4,"average_cadence":78.1,"device_watts":false,"average_heartrate":146.3,"max_heartrate":174,"lap_index":1,"split":1,"pace_zone":0},{"id":15864776367,"resource_state":2,"name":"Lap 2","activity":{"id":4854101189,"resource_state":1},"athlete":{"id":42223740,"resource_state":1},"elapsed_time":185,"moving_time":182,"start_date":"2021-02-26T11:28:15Z","start_date_local":"2021-02-26T12:28:15Z","distance":445.93,"start_index":100,"end_index":144,"total_elevation_gain":14,"average_speed":2.45,"max_speed":3.1,"average_cadence":77.4,"device_watts":false,"average_heartrate":152.2,"max_heartrate":161,"lap_index":2,"split":2,"pace_zone":0},{"id":15864776378,"resource_state":2,"name":"Lap 3","activity":{"id":4854101189,"resource_state":1},"athlete":{"id":42223740,"resource_state":1},"elapsed_time":30,"moving_time":30,"start_date":"2021-02-26T11:31:23Z","start_date_local":"2021-02-26T12:31:23Z","distance":79.15,"start_index":145,"end_index":150,"total_elevation_gain":0,"average_speed":2.64,"max_speed":2.7,"average_cadence":77.7,"device_watts":false,"average_heartrate":158.3,"max_heartrate":160,"lap_index":3,"split":3,"pace_zone":0},{"id":15864776397,"resource_state":2,"name":"Lap 4","activity":{"id":4854101189,"resource_state":1},"athlete":{"id":42223740,"resource_state":1},"elapsed_time":30,"moving_time":30,"start_date":"2021-02-26T11:31:55Z","start_date_local":"2021-02-26T12:31:55Z","distance":69.41,"start_index":151,"end_index":156,"total_elevation_gain":0,"average_speed":2.31,"max_speed":2.5,"average_cadence":77,"device_watts":false,"average_heartrate":163.1,"max_heartrate":164,"lap_index":4,"split":4,"pace_zone":0},{"id":15864776408,"resource_state":2,"name":"Lap 5","activity":{"id":4854101189,"resource_state":1},"athlete":{"id":42223740,"resource_state":1},"elapsed_time":30,"moving_time":30,"start_date":"2021-02-26T11:32:24Z","start_date_local":"2021-02-26T12:32:24Z","distance":80.53,"start_index":157,"end_index":164,"total_elevation_gain":5,"average_speed":2.68,"max_speed":2.7,"average_cadence":77.8,"device_watts":false,"average_heartrate":162.1,"max_heartrate":163,"lap_index":5,"split":5,"pace_zone":0},{"id":15864776421,"resource_state":2,"name":"Lap 6","activity":{"id":4854101189,"resource_state":1},"athlete":{"id":42223740,"resource_state":1},"elapsed_time":30,"moving_time":30,"start_date":"2021-02-26T11:32:54Z","start_date_local":"2021-02-26T12:32:54Z","distance":69.54,"start_index":165,"end_index":172,"total_elevation_gain":0,"average_speed":2.32,"max_speed":2.6,"average_cadence":77.7,"device_watts":false,"average_heartrate":163.8,"max_heartrate":164,"lap_index":6,"split":6,"pace_zone":0},{"id":15864776437,"resource_state":2,"name":"Lap 7","activity":{"id":4854101189,"resource_state":1},"athlete":{"id":42223740,"resource_state":1},"elapsed_time":30,"moving_time":30,"start_date":"2021-02-26T11:33:26Z","start_date_local":"2021-02-26T12:33:26Z","distance":75.73,"start_index":173,"end_index":177,"total_elevation_gain":3,"average_speed":2.52,"max_speed":2.8,"average_cadence":77.8,"device_watts":false,"average_heartrate":165.5,"max_heartrate":167,"lap_index":7,"split":7,"pace_zone":0},{"id":15864776447,"resource_state":2,"name":"Lap 8","activity":{"id":4854101189,"resource_state":1},"athlete":{"id":42223740,"resource_state":1},"elapsed_time":30,"moving_time":30,"start_date":"2021-02-26T11:33:52Z","start_date_local":"2021-02-26T12:33:52Z","distance":64.74,"start_index":178,"end_index":183,"total_elevation_gain":4,"average_speed":2.16,"max_speed":2.5,"average_cadence":76.6,"device_watts":false,"average_heartrate":163.9,"max_heartrate":164,"lap_index":8,"split":8,"pace_zone":0},{"id":15864776458,"resource_state":2,"name":"Lap 9","activity":{"id":4854101189,"resource_state":1},"athlete":{"id":42223740,"resource_state":1},"elapsed_time":30,"moving_time":30,"start_date":"2021-02-26T11:34:25Z","start_date_local":"2021-02-26T12:34:25Z","distance":75.46,"start_index":184,"end_index":189,"total_elevation_gain":1,"average_speed":2.52,"max_speed":2.7,"average_cadence":77.8,"device_watts":false,"average_heartrate":165,"max_heartrate":167,"lap_index":9,"split":9,"pace_zone":0},{"id":15864776469,"resource_state":2,"name":"Lap 10","activity":{"id":4854101189,"resource_state":1},"athlete":{"id":42223740,"resource_state":1},"elapsed_time":30,"moving_time":30,"start_date":"2021-02-26T11:34:55Z","start_date_local":"2021-02-26T12:34:55Z","distance":64.81,"start_index":190,"end_index":193,"total_elevation_gain":4,"average_speed":2.16,"max_speed":2.2,"average_cadence":75.6,"device_watts":false,"average_heartrate":165.6,"max_heartrate":166,"lap_index":10,"split":10,"pace_zone":0},{"id":15864776486,"resource_state":2,"name":"Lap 11","activity":{"id":4854101189,"resource_state":1},"athlete":{"id":42223740,"resource_state":1},"elapsed_time":30,"moving_time":30,"start_date":"2021-02-26T11:35:27Z","start_date_local":"2021-02-26T12:35:27Z","distance":79.27,"start_index":194,"end_index":200,"total_elevation_gain":10,"average_speed":2.64,"max_speed":2.8,"average_cadence":77.7,"device_watts":false,"average_heartrate":165.3,"max_heartrate":167,"lap_index":11,"split":11,"pace_zone":0},{"id":15864776499,"resource_state":2,"name":"Lap 12","activity":{"id":4854101189,"resource_state":1},"athlete":{"id":42223740,"resource_state":1},"elapsed_time":30,"moving_time":30,"start_date":"2021-02-26T11:35:55Z","start_date_local":"2021-02-26T12:35:55Z","distance":69.58,"start_index":201,"end_index":205,"total_elevation_gain":0,"average_speed":2.32,"max_speed":2.7,"average_cadence":76.7,"device_watts":false,"average_heartrate":166,"max_heartrate":167,"lap_index":12,"split":12,"pace_zone":0},{"id":15864776511,"resource_state":2,"name":"Lap 13","activity":{"id":4854101189,"resource_state":1},"athlete":{"id":42223740,"resource_state":1},"elapsed_time":30,"moving_time":30,"start_date":"2021-02-26T11:36:26Z","start_date_local":"2021-02-26T12:36:26Z","distance":81.07,"start_index":206,"end_index":212,"total_elevation_gain":0,"average_speed":2.7,"max_speed":3,"average_cadence":77.7,"device_watts":false,"average_heartrate":159.2,"max_heartrate":165,"lap_index":13,"split":13,"pace_zone":0},{"id":15864776524,"resource_state":2,"name":"Lap 14","activity":{"id":4854101189,"resource_state":1},"athlete":{"id":42223740,"resource_state":1},"elapsed_time":30,"moving_time":30,"start_date":"2021-02-26T11:36:54Z","start_date_local":"2021-02-26T12:36:54Z","distance":68.43,"start_index":213,"end_index":219,"total_elevation_gain":5,"average_speed":2.28,"max_speed":2.4,"average_cadence":76.5,"device_watts":false,"average_heartrate":163.3,"max_heartrate":166,"lap_index":14,"split":14,"pace_zone":0},{"id":15864776534,"resource_state":2,"name":"Lap 15","activity":{"id":4854101189,"resource_state":1},"athlete":{"id":42223740,"resource_state":1},"elapsed_time":30,"moving_time":30,"start_date":"2021-02-26T11:37:21Z","start_date_local":"2021-02-26T12:37:21Z","distance":75.94,"start_index":220,"end_index":226,"total_elevation_gain":0,"average_speed":2.53,"max_speed":2.8,"average_cadence":77.1,"device_watts":false,"average_heartrate":164.4,"max_heartrate":166,"lap_index":15,"split":15,"pace_zone":0},{"id":15864776544,"resource_state":2,"name":"Lap 16","activity":{"id":4854101189,"resource_state":1},"athlete":{"id":42223740,"resource_state":1},"elapsed_time":30,"moving_time":30,"start_date":"2021-02-26T11:37:55Z","start_date_local":"2021-02-26T12:37:55Z","distance":65.76,"start_index":227,"end_index":232,"total_elevation_gain":3,"average_speed":2.19,"max_speed":2.4,"average_cadence":76,"device_watts":false,"average_heartrate":165.1,"max_heartrate":166,"lap_index":16,"split":16,"pace_zone":0},{"id":15864776550,"resource_state":2,"name":"Lap 17","activity":{"id":4854101189,"resource_state":1},"athlete":{"id":42223740,"resource_state":1},"elapsed_time":30,"moving_time":30,"start_date":"2021-02-26T11:38:23Z","start_date_local":"2021-02-26T12:38:23Z","distance":74.71,"start_index":233,"end_index":238,"total_elevation_gain":0,"average_speed":2.49,"max_speed":2.6,"average_cadence":77.2,"device_watts":false,"average_heartrate":165.9,"max_heartrate":168,"lap_index":17,"split":17,"pace_zone":0},{"id":15864776561,"resource_state":2,"name":"Lap 18","activity":{"id":4854101189,"resource_state":1},"athlete":{"id":42223740,"resource_state":1},"elapsed_time":30,"moving_time":30,"start_date":"2021-02-26T11:38:56Z","start_date_local":"2021-02-26T12:38:56Z","distance":69.07,"start_index":239,"end_index":242,"total_elevation_gain":5,"average_speed":2.3,"max_speed":2.5,"average_cadence":76,"device_watts":false,"average_heartrate":167,"max_heartrate":168,"lap_index":18,"split":18,"pace_zone":0},{"id":15864776569,"resource_state":2,"name":"Lap 19","activity":{"id":4854101189,"resource_state":1},"athlete":{"id":42223740,"resource_state":1},"elapsed_time":30,"moving_time":30,"start_date":"2021-02-26T11:39:21Z","start_date_local":"2021-02-26T12:39:21Z","distance":80.31,"start_index":243,"end_index":247,"total_elevation_gain":6,"average_speed":2.68,"max_speed":2.7,"average_cadence":77.7,"device_watts":false,"average_heartrate":167.2,"max_heartrate":168,"lap_index":19,"split":19,"pace_zone":0},{"id":15864776580,"resource_state":2,"name":"Lap 20","activity":{"id":4854101189,"resource_state":1},"athlete":{"id":42223740,"resource_state":1},"elapsed_time":30,"moving_time":30,"start_date":"2021-02-26T11:39:57Z","start_date_local":"2021-02-26T12:39:57Z","distance":72.27,"start_index":248,"end_index":253,"total_elevation_gain":0,"average_speed":2.41,"max_speed":2.6,"average_cadence":77,"device_watts":false,"average_heartrate":166.7,"max_heartrate":168,"lap_index":20,"split":20,"pace_zone":0},{"id":15864776590,"resource_state":2,"name":"Lap 21","activity":{"id":4854101189,"resource_state":1},"athlete":{"id":42223740,"resource_state":1},"elapsed_time":30,"moving_time":30,"start_date":"2021-02-26T11:40:23Z","start_date_local":"2021-02-26T12:40:23Z","distance":77.65,"start_index":254,"end_index":260,"total_elevation_gain":3,"average_speed":2.59,"max_speed":2.9,"average_cadence":78,"device_watts":false,"average_heartrate":168,"max_heartrate":169,"lap_index":21,"split":21,"pace_zone":0},{"id":15864776603,"resource_state":2,"name":"Lap 22","activity":{"id":4854101189,"resource_state":1},"athlete":{"id":42223740,"resource_state":1},"elapsed_time":30,"moving_time":30,"start_date":"2021-02-26T11:40:54Z","start_date_local":"2021-02-26T12:40:54Z","distance":75.59,"start_index":261,"end_index":267,"total_elevation_gain":1,"average_speed":2.52,"max_speed":2.6,"average_cadence":76.9,"device_watts":false,"average_heartrate":168.6,"max_heartrate":169,"lap_index":22,"split":22,"pace_zone":0},{"id":15864776615,"resource_state":2,"name":"Lap 23","activity":{"id":4854101189,"resource_state":1},"athlete":{"id":42223740,"resource_state":1},"elapsed_time":299,"moving_time":299,"start_date":"2021-02-26T11:41:26Z","start_date_local":"2021-02-26T12:41:26Z","distance":630.12,"start_index":268,"end_index":317,"total_elevation_gain":25,"average_speed":2.11,"max_speed":2.6,"average_cadence":75,"device_watts":false,"average_heartrate":166,"max_heartrate":169,"lap_index":23,"split":23,"pace_zone":0}],"best_efforts":[{"id":10100364706,"resource_state":2,"name":"400m","activity":{"id":4854101189,"resource_state":1},"athlete":{"id":42223740,"resource_state":1},"elapsed_time":151,"moving_time":152,"start_date":"2021-02-26T11:22:18Z","start_date_local":"2021-02-26T12:22:18Z","distance":400,"start_index":19,"end_index":59,"pr_rank":null,"achievements":[]},{"id":10100364710,"resource_state":2,"name":"1/2 mile","activity":{"id":4854101189,"resource_state":1},"athlete":{"id":42223740,"resource_state":1},"elapsed_time":316,"moving_time":317,"start_date":"2021-02-26T11:21:44Z","start_date_local":"2021-02-26T12:21:44Z","distance":805,"start_index":10,"end_index":80,"pr_rank":null,"achievements":[]},{"id":10100364718,"resource_state":2,"name":"1k","activity":{"id":4854101189,"resource_state":1},"athlete":{"id":42223740,"resource_state":1},"elapsed_time":398,"moving_time":399,"start_date":"2021-02-26T11:22:06Z","start_date_local":"2021-02-26T12:22:06Z","distance":1000,"start_index":17,"end_index":107,"pr_rank":null,"achievements":[]},{"id":10100364724,"resource_state":2,"name":"1 mile","activity":{"id":4854101189,"resource_state":1},"athlete":{"id":42223740,"resource_state":1},"elapsed_time":648,"moving_time":649,"start_date":"2021-02-26T11:22:06Z","start_date_local":"2021-02-26T12:22:06Z","distance":1609,"start_index":17,"end_index":166,"pr_rank":null,"achievements":[]},{"id":10100364733,"resource_state":2,"name":"2 mile","activity":{"id":4854101189,"resource_state":1},"athlete":{"id":42223740,"resource_state":1},"elapsed_time":1332,"moving_time":1333,"start_date":"2021-02-26T11:21:32Z","start_date_local":"2021-02-26T12:21:32Z","distance":3219,"start_index":1,"end_index":293,"pr_rank":null,"achievements":[]}],"photos":{"primary":null,"count":0},"stats_visibility":[{"type":"heart_rate","visibility":"everyone"},{"type":"pace","visibility":"everyone"},{"type":"power","visibility":"everyone"},{"type":"speed","visibility":"everyone"},{"type":"calories","visibility":"everyone"}],"hide_from_home":false,"device_name":"Garmin Forerunner 245","embed_token":"5b142ba7b486098fe3682e3915b14e0bdb1d0ac5","similar_activities":{"effort_count":1,"average_speed":2.3823924731182795,"min_average_speed":2.3823924731182795,"mid_average_speed":2.3823924731182795,"max_average_speed":2.3823924731182795,"pr_rank":null,"frequency_milestone":null,"trend":{"speeds":[2.3823924731182795],"current_activity_index":0,"min_speed":2.3823924731182795,"mid_speed":2.3823924731182795,"max_speed":2.3823924731182795,"direction":0},"resource_state":2},"available_zones":[]}